grepimports/__init__.py
grepimports/__main__.py
grepimports-0.0.1.dist-info/LICENSE
grepimports-0.0.1.dist-info/METADATA
grepimports-0.0.1.dist-info/WHEEL
grepimports-0.0.1.dist-info/entry_points.txt
grepimports-0.0.1.dist-info/top_level.txt
grepimports-0.0.1.dist-info/RECORD
