Metadata-Version: 2.1
Name: grepimports
Version: 0.0.1
Summary: Greps sources for imports and prints dependencies as list of package names
Home-page: https://github.com/mugiseyebrows/grep-imports
Author: Stanislav Doronin
Author-email: mugisbrows@gmail.com
License: UNKNOWN
Platform: UNKNOWN
Requires-Dist: importlib-metadata
